AUTHORS
COPYING
MANIFEST.in
README
development.ini
orbited.cfg
setup.py
moksha/__init__.py
moksha.feeds.egg-info/PKG-INFO
moksha.feeds.egg-info/SOURCES.txt
moksha.feeds.egg-info/dependency_links.txt
moksha.feeds.egg-info/entry_points.txt
moksha.feeds.egg-info/namespace_packages.txt
moksha.feeds.egg-info/requires.txt
moksha.feeds.egg-info/top_level.txt
moksha/feeds/__init__.py
moksha/feeds/lib.py
moksha/feeds/tests/__init__.py
moksha/feeds/tests/test_feed.py
moksha/feeds/tests/templates/__init__.py
moksha/feeds/widgets/__init__.py
moksha/feeds/widgets/feed.py
moksha/feeds/widgets/live.py
moksha/feeds/widgets/templates/__init__.py